apclib/__init__.py
apclib/controllers.py
apclib/datagen.py
apclib/io.py
apclib/models.py
apclib/plotting.py
apclib/signalprocessing.py
apclib/systemid.py
apclib-0.0.4.dist-info/METADATA
apclib-0.0.4.dist-info/WHEEL
apclib-0.0.4.dist-info/entry_points.txt
apclib-0.0.4.dist-info/license_files/LICENSE
apclib-0.0.4.dist-info/RECORD
